randomsubgroups/__init__.py
randomsubgroups/_randomsubgroups.py
randomsubgroups/_version.py
randomsubgroups/pysubgrouputils.py
randomsubgroups/subgroup.py
randomsubgroups/subgroup_predictor.py
randomsubgroups/test__randomsubgroups.py
random_subgroups-0.4.1.dist-info/LICENSE
random_subgroups-0.4.1.dist-info/METADATA
random_subgroups-0.4.1.dist-info/WHEEL
random_subgroups-0.4.1.dist-info/top_level.txt
random_subgroups-0.4.1.dist-info/RECORD
